slackify/__init__.py
slackify/blueprint.py
slackify/dip.py
slackify/dispatcher.py
slackify/flack.py
slackify/injection.py
slackify/injector.py
slackify/main.py
slackify/slack.py
slackify/tasks.py
slackify/__pycache__/__init__.cpython-38.pyc
slackify/__pycache__/dip.cpython-38.pyc
slackify/__pycache__/dispatcher.cpython-38.pyc
slackify/__pycache__/flack.cpython-38.pyc
slackify/__pycache__/slack.cpython-38.pyc
slackify/__pycache__/tasks.cpython-38.pyc
slackify-1.0.0.dist-info/LICENSE
slackify-1.0.0.dist-info/METADATA
slackify-1.0.0.dist-info/WHEEL
slackify-1.0.0.dist-info/top_level.txt
slackify-1.0.0.dist-info/RECORD
